setup.py
Mydemos_pkg/ASCII.py
Mydemos_pkg/MyHelp.py
Mydemos_pkg/__init__.py
Mydemos_pkg/bytedesign.py
Mydemos_pkg/chaos.py
Mydemos_pkg/clock.py
Mydemos_pkg/colormixer.py
Mydemos_pkg/colorspiral.py
Mydemos_pkg/core.py
Mydemos_pkg/download_file.py
Mydemos_pkg/forest.py
Mydemos_pkg/fractalcurves.py
Mydemos_pkg/hanoi.py
Mydemos_pkg/lindenmayer.py
Mydemos_pkg/nim.py
Mydemos_pkg/paint.py
Mydemos_pkg/peace.py
Mydemos_pkg/penrose.py
Mydemos_pkg/pip_install.py
Mydemos_pkg/planet_and_moon.py
Mydemos_pkg/progress.py
Mydemos_pkg/rosette.py
Mydemos_pkg/round_dance.py
Mydemos_pkg/run.py
Mydemos_pkg/sort.py
Mydemos_pkg/sort_animate.py
Mydemos_pkg/sort_test_cn.py
Mydemos_pkg/tree.py
Mydemos_pkg/two_canvas.py
Mydemos_pkg/unicodeconvert.py
Mydemos_pkg/unicodemap.py
Mydemos_pkg/unicodeprint.py
Mydemos_pkg/unicodes.py
Mydemos_pkg/yinyang.py
Mydemos_pkg-1.2.7.30.dist-info/METADATA
Mydemos_pkg-1.2.7.30.dist-info/WHEEL
Mydemos_pkg-1.2.7.30.dist-info/top_level.txt
Mydemos_pkg-1.2.7.30.dist-info/RECORD
