Metadata-Version: 2.1
Name: Mydemos-pkg
Version: 1.2.7.30
Summary: a small pkg demos for you and everyone
Home-page: UNKNOWN
License: UNKNOWN
Platform: UNKNOWN
